mongo_api_client/MongoApiClient.py
mongo_api_client/MongoApiResponse.py
mongo_api_client/MongoApiResponseData.py
mongo_api_client/MongoApiResponsePagination.py
mongo_api_client/__init__.py
mongo_api_client-1.0.dist-info/METADATA
mongo_api_client-1.0.dist-info/WHEEL
mongo_api_client-1.0.dist-info/top_level.txt
mongo_api_client-1.0.dist-info/RECORD
