Metadata-Version: 2.4
Name: mongo-api-client
Version: 1.0
Summary: Provides a fluent syntax for interacting with a MongoDB API Instance
Home-page: https://github.com/alexanderthegreat96/mongo-api-python-client
Author: alexanderthegreat96
Author-email: alexanderdth96@gmail.com
Classifier: Programming Language :: Python :: 3
Classifier: License :: OSI Approved :: MIT License
Classifier: Operating System :: OS Independent
Requires-Python: >=3.10
Requires-Dist: requests
Dynamic: author
Dynamic: author-email
Dynamic: classifier
Dynamic: description
Dynamic: description-content-type
Dynamic: home-page
Dynamic: requires-dist
Dynamic: requires-python
Dynamic: summary
